Metadata-Version: 2.4
Name: inMOTIFin
Version: 4.1.0
Summary: inMOTIFin
Home-page: https://bitbucket.org/CBGR/inmotifin/src/main/
Author: Katalin Ferenc
Author-email: katalitf@uio.no
License: MIT license
Keywords: inMOTIFin
Classifier: Development Status :: 2 - Pre-Alpha
Classifier: Intended Audience :: Developers
Classifier: License :: OSI Approved :: MIT License
Classifier: Natural Language :: English
Classifier: Programming Language :: Python :: 3.10
Requires-Python: >=3.9
License-File: LICENSE
Requires-Dist: click
Requires-Dist: numpy
Requires-Dist: pandas
Requires-Dist: dagsim
Requires-Dist: pyjaspar
Requires-Dist: biopython
Requires-Dist: hmmlearn
Dynamic: author
Dynamic: author-email
Dynamic: classifier
Dynamic: description
Dynamic: description-content-type
Dynamic: home-page
Dynamic: keywords
Dynamic: license
Dynamic: license-file
Dynamic: requires-dist
Dynamic: requires-python
Dynamic: summary
